nuclio_sdk/__init__.py
nuclio_sdk/context.py
nuclio_sdk/event.py
nuclio_sdk/exceptions.py
nuclio_sdk/helpers.py
nuclio_sdk/json_encoder.py
nuclio_sdk/logger.py
nuclio_sdk/platform.py
nuclio_sdk/qualified_offset.py
nuclio_sdk/response.py
nuclio_sdk/test/__init__.py
nuclio_sdk/test/mock_platform.py
nuclio_sdk/test/test_case.py
nuclio_sdk/test/test_event.py
nuclio_sdk/test/test_logger.py
nuclio_sdk/test/test_qualified_offset.py
nuclio_sdk/test/test_response.py
nuclio_sdk/test/test_streaming.py
nuclio_sdk-0.6.2.dist-info/licenses/LICENSE.txt
nuclio_sdk-0.6.2.dist-info/METADATA
nuclio_sdk-0.6.2.dist-info/WHEEL
nuclio_sdk-0.6.2.dist-info/top_level.txt
nuclio_sdk-0.6.2.dist-info/RECORD
